.DS_Store
scRFE/__init__.py
scRFE/scRFE.py
scRFE/utils.py
scRFE-1.3.dist-info/LICENSE
scRFE-1.3.dist-info/METADATA
scRFE-1.3.dist-info/WHEEL
scRFE-1.3.dist-info/top_level.txt
scRFE-1.3.dist-info/RECORD
