Metadata-Version: 2.1
Name: scRFE
Version: 1.3
Summary: Single-cell identity definition using random forest modelling and recursive feature elimination
Home-page: https://github.com/czbiohub/scRFE
Author: Madeline Park
Author-email: madeline.park@czbiohub.org
License: MIT Licence
Keywords: pip,single cell,scRFE
Platform: any
Requires-Dist: anndata (>=0.6.21)
Requires-Dist: matplotlib (>=3.1.1)
Requires-Dist: numpy (>=1.16.4)
Requires-Dist: scikit-learn (>=0.20.3)
Requires-Dist: scanpy (>=1.4.3)
Requires-Dist: pandas (>=0.24.2)
